isingcpu.cpython-35m-x86_64-linux-gnu.so
ising-0.1.23.dist-info/WHEEL
ising-0.1.23.dist-info/top_level.txt
ising-0.1.23.dist-info/METADATA
ising-0.1.23.dist-info/RECORD
ising/helpers.py
ising/__init__.py
ising/core.py
ising/graphtools.py
.libsisingcpu/libgomp-3300acd3.so.1.0.0
.libsisingcpu/libgfortran-ed201abd.so.3.0.0
