Metadata-Version: 2.1
Name: ising
Version: 0.1.23
Summary: Ising: a Python package for exactly solving abritrary Ising model instances using exhaustive search.
Home-page: UNKNOWN
Author: UNKNOWN
Author-email: UNKNOWN
License: UNKNOWN
Platform: UNKNOWN
Requires-Dist: numpy (>=0.16.0)
Requires-Dist: psutil
Requires-Dist: progressbar2
Requires-Dist: future
